chromepilot/__init__.py
chromepilot/__main__.py
chromepilot/api.py
chromepilot/cli.py
chromepilot/local.py
chromepilot/pilot.toml
chromepilot/short.py
chromepilot/utils.py
chromepilot-1.0.0.dist-info/METADATA
chromepilot-1.0.0.dist-info/WHEEL
chromepilot-1.0.0.dist-info/entry_points.txt
chromepilot-1.0.0.dist-info/top_level.txt
chromepilot-1.0.0.dist-info/RECORD
