Metadata-Version: 2.1
Name: chromepilot
Version: 1.0.0
Summary: Chromedriver download manager and imports shortcuts.
Home-page: https://github.com/HenriquedoVal/chromepilot
Author: Henrique do Val
Author-email: henrique.val@hotmail.com
Requires-Python: >=3.8
